pb_api/__init__.py
pb_api/commands/base.py
pb_api/commands/color.py
pb_api/commands/control_mode.py
pb_api/commands/luminosity.py
pb_api/commands/system_config.py
pb_api/core/constants.py
pb_api/core/device_manager.py
pb_api/core/exceptions.py
pb_api/core/protocol.py
pb_api/examples/basic_usage.py
pb_api/examples/color_effect.py
pb_api/examples/color_transition.py
pb_api/examples/quick_example.py
pb_api/examples/quick_start.py
pb_api/models/device_state.py
push_button_light_control-1.1.4.dist-info/METADATA
push_button_light_control-1.1.4.dist-info/WHEEL
push_button_light_control-1.1.4.dist-info/entry_points.txt
push_button_light_control-1.1.4.dist-info/top_level.txt
push_button_light_control-1.1.4.dist-info/RECORD
