Metadata-Version: 2.4
Name: push-button-light-control
Version: 1.1.4
Summary: API for PIC24FV-based Push button Light Control System
Author: Basit Akram
Author-email: Basit Akram <basit.akram@gaengineering.com>
License: MIT
Keywords: led,controller,serial,uart,protocol,pic24fv
Classifier: Development Status :: 5 - Production/Stable
Classifier: Intended Audience :: Developers
Classifier: Intended Audience :: End Users/Desktop
Classifier: License :: OSI Approved :: MIT License
Classifier: Operating System :: OS Independent
Classifier: Programming Language :: Python :: 3
Classifier: Programming Language :: Python :: 3.7
Classifier: Programming Language :: Python :: 3.8
Classifier: Programming Language :: Python :: 3.9
Classifier: Programming Language :: Python :: 3.10
Classifier: Programming Language :: Python :: 3.11
Classifier: Topic :: Scientific/Engineering :: Interface Engine/Protocol Translator
Requires-Python: >=3.7
Requires-Dist: pyserial>=3.5
Provides-Extra: dev
Requires-Dist: twine>=4.0.0; extra == "dev"
Requires-Dist: build>=0.10.0; extra == "dev"
Dynamic: author
Dynamic: requires-python
